{
    "Entities": [
        {
            "clientOnly": 0,
            "color": {
                "blue": 174,
                "green": 255,
                "red": 0
            },
            "created": "2016-11-02T22:58:37Z",
            "dimensions": {
                "x": 0.20000000298023224,
                "y": 0.040637210011482239,
                "z": 0.20000000298023224
            },
            "id": "{44e1a7da-8bc0-4958-a92f-4c09b7deadf3}",
            "name": "greenpadding",
            "owningAvatarID": "{00000000-0000-0000-0000-000000000000}",
            "position": {
                "x": 0.0090069770812988281,
                "y": 0.6615142822265625,
                "z": 0.00032806396484375
            },
            "queryAACube": {
                "scale": 0.28574708104133606,
                "x": -0.1338665634393692,
                "y": 0.51864075660705566,
                "z": -0.14254547655582428
            },
            "type": "Sphere"
        },
        {
            "clientOnly": 0,
            "color": {
                "blue": 174,
                "green": 255,
                "red": 0
            },
            "created": "2016-11-02T22:58:37Z",
            "dimensions": {
                "x": 0.20000000298023224,
                "y": 0.040637210011482239,
                "z": 0.20000000298023224
            },
            "id": "{87220831-aae8-454e-8334-9e230ab1aaf3}",
            "name": "greenpadding",
            "owningAvatarID": "{00000000-0000-0000-0000-000000000000}",
            "position": {
                "x": 0.0090069770812988281,
                "y": 0.55767822265625,
                "z": 0.00032806396484375
            },
            "queryAACube": {
                "scale": 0.28574708104133606,
                "x": -0.1338665634393692,
                "y": 0.41480469703674316,
                "z": -0.14254547655582428
            },
            "type": "Sphere"
        },
        {
            "clientOnly": 0,
            "color": {
                "blue": 220,
                "green": 220,
                "red": 220
            },
            "created": "2016-11-02T22:19:18Z",
            "dimensions": {
                "x": 0.20000000298023224,
                "y": 0.20000000298023224,
                "z": 0.20000000298023224
            },
            "id": "{c2d41afe-54a2-47ba-a0e0-3dba4c4632af}",
            "marketplaceID": "128b8eac-e70e-4980-91b2-df8f4940edc8",
            "name": "QuorraBall",
            "owningAvatarID": "{00000000-0000-0000-0000-000000000000}",
            "position": {
                "x": 0.0055913925170898438,
                "y": 0.5777435302734375,
                "z": 0.002742767333984375
            },
            "queryAACube": {
                "scale": 0.34641015529632568,
                "x": -0.167613685131073,
                "y": 0.40453845262527466,
                "z": -0.17046231031417847
            },
            "rotation": {
                "w": 0.7070959210395813,
                "x": 9.0949470177292824e-13,
                "y": -0.70711761713027954,
                "z": -2.1579184249276295e-05
            },
            "type": "Sphere",
            "userData": "{\"ProceduralEntity\":{\"version\":2,\"shaderUrl\":\"https://s3.amazonaws.com/Oculus/shadertoys/quora2.fs\",\"uniforms\":{\"iSpeed\":1,\"iShell\":0.4}}}"
        },
        {
            "clientOnly": 0,
            "color": {
                "blue": 220,
                "green": 220,
                "red": 220
            },
            "created": "2016-11-02T22:19:18Z",
            "dimensions": {
                "x": 0.13333334028720856,
                "y": 0.13333334028720856,
                "z": 0.13333334028720856
            },
            "id": "{499cf1a9-1419-4119-8524-b9782770c8c5}",
            "marketplaceID": "128b8eac-e70e-4980-91b2-df8f4940edc8",
            "name": "QuorraBall",
            "owningAvatarID": "{00000000-0000-0000-0000-000000000000}",
            "position": {
                "x": 0.010961532592773438,
                "y": 0.5777435302734375,
                "z": 0.00093173980712890625
            },
            "queryAACube": {
                "scale": 0.23094013333320618,
                "x": -0.10450853407382965,
                "y": 0.46227347850799561,
                "z": -0.11453832685947418
            },
            "rotation": {
                "w": 0.9238736629486084,
                "x": -8.2579963418538682e-06,
                "y": -0.38269755244255066,
                "z": -1.9936567696277052e-05
            },
            "type": "Sphere",
            "userData": "{\"ProceduralEntity\":{\"version\":2,\"shaderUrl\":\"https://s3.amazonaws.com/Oculus/shadertoys/quora2.fs\",\"uniforms\":{\"iSpeed\":1,\"iShell\":0.2666666666666667}}}"
        },
        {
            "clientOnly": 0,
            "created": "2016-11-02T22:04:00Z",
            "dimensions": {
                "x": 0.20000000298023224,
                "y": 1.1218292713165283,
                "z": 0.20000000298023224
            },
            "id": "{0e94b09d-0bfb-480b-98d2-84e33fc9972a}",
            "owningAvatarID": "{00000000-0000-0000-0000-000000000000}",
            "position": {
                "x": 0.0092496871948242188,
                "y": 0,
                "z": 0
            },
            "queryAACube": {
                "scale": 1.1569359302520752,
                "x": -0.56921827793121338,
                "y": -0.5784679651260376,
                "z": -0.5784679651260376
            },
            "rotation": {
                "w": 0.92387950420379639,
                "x": 0,
                "y": -0.38268345594406128,
                "z": 0
            },
            "shape": "Cube",
            "type": "Box"
        },
        {
            "clientOnly": 0,
            "color": {
                "blue": 220,
                "green": 220,
                "red": 220
            },
            "created": "2016-11-02T22:19:18Z",
            "dimensions": {
                "x": 0.1666666716337204,
                "y": 0.1666666716337204,
                "z": 0.1666666716337204
            },
            "id": "{8a1ebf28-0f6c-4a2e-9a69-27f0ea6a80ba}",
            "marketplaceID": "128b8eac-e70e-4980-91b2-df8f4940edc8",
            "name": "QuorraBall",
            "owningAvatarID": "{00000000-0000-0000-0000-000000000000}",
            "position": {
                "x": 0.005100250244140625,
                "y": 0.5777435302734375,
                "z": 0.0021800994873046875
            },
            "queryAACube": {
                "scale": 0.28867515921592712,
                "x": -0.13923732936382294,
                "y": 0.43340593576431274,
                "z": -0.14215748012065887
            },
            "rotation": {
                "w": 0.81883770227432251,
                "x": 0.28194251656532288,
                "y": -0.4727649986743927,
                "z": -0.16280809044837952
            },
            "type": "Sphere",
            "userData": "{\"ProceduralEntity\":{\"version\":2,\"shaderUrl\":\"https://s3.amazonaws.com/Oculus/shadertoys/quora2.fs\",\"uniforms\":{\"iSpeed\":1,\"iShell\":0.33333333333333337}}}"
        },
        {
            "backgroundColor": {
                "blue": 174,
                "green": 255,
                "red": 0
            },
            "clientOnly": 0,
            "created": "2016-11-02T22:23:40Z",
            "dimensions": {
                "x": 0.087855219841003418,
                "y": 0.092474333941936493,
                "z": 0.0099999997764825821
            },
            "id": "{7bc79fca-e6b5-4bdc-a272-04d5e210911b}",
            "lineHeight": 0.059999998658895493,
            "owningAvatarID": "{00000000-0000-0000-0000-000000000000}",
            "position": {
                "x": 0,
                "y": 0.683624267578125,
                "z": 0.010362625122070312
            },
            "queryAACube": {
                "scale": 0.12794546782970428,
                "x": -0.063972733914852142,
                "y": 0.61965155601501465,
                "z": -0.05361010879278183
            },
            "rotation": {
                "w": 0.65161633491516113,
                "x": -0.65161633491516113,
                "y": -0.27458363771438599,
                "z": -0.27458363771438599
            },
            "text": "OK",
            "type": "Text"
        }
    ],
    "Version": 64
}
